MANIFEST.in
README.md
setup.py
cloudcast/__init__.py
cloudcast/_utils.py
cloudcast/elements.py
cloudcast/template.py
cloudcast.egg-info/PKG-INFO
cloudcast.egg-info/SOURCES.txt
cloudcast.egg-info/dependency_links.txt
cloudcast.egg-info/not-zip-safe
cloudcast.egg-info/requires.txt
cloudcast.egg-info/top_level.txt
cloudcast/iscm/__init__.py
cloudcast/iscm/ansible.py
cloudcast/iscm/cfninit.py
cloudcast/iscm/phased.py
cloudcast/iscm/shell.py
cloudcast/iscm/scripts/init.sh
cloudcast/iscm/scripts/install_ansible.sh
cloudcast/library/__init__.py
cloudcast/library/stack_user.py