Metadata-Version: 1.1
Name: cloudcast
Version: 0.1.2
Summary: Easy and powerful stack templates for AWS CloudFormation
Home-page: http://github.com/tuxpiper/cloudcast
Author: David Losada Carballo
Author-email: david@tuxpiper.com
License: MIT
Keywords: aws internet cloud cloudformation deployment automation
Platform: UNKNOWN
Classifier: Development Status :: 3 - Alpha
Classifier: Topic :: System
Classifier: Environment :: Console
Classifier: Intended Audience :: System Administrators
Classifier: License :: OSI Approved :: MIT License
Classifier: Programming Language :: Python
